Workbook

Sheet Assumptions
A1: Skill thermostat: revenue model assumptions
A2: Every number here is an assumption I chose for illustration, not market data. Blue = input you can change. Yellow = the assumptions that move the result most. Years are after a successful human pilot.
A4: Assumption | B4: Year 1 | C4: Year 2 | D4: Year 3 | E4: Note
A5: Paid pilots (count) | B5: 3 | C5: 0 | D5: 0 | E5: Fee-based pilots run for a customer. Early revenue.
A6: Fee per pilot ($) | B6: 10000 | C6: 10000 | D6: 10000 | E6: Midpoint of an assumed $5k-$15k range.
A7: School customers (active) | B7: 0 | C7: 10 | D7: 40 | E7: Bootcamps, departments, universities.
A8: Seats per school customer | B8: 200 | C8: 200 | D8: 200 | E8: Students per customer.
A9: School price ($ per seat per month) | B9: 5 | C9: 5 | D9: 5 | E9: Assumed.
A10: School months billed per year | B10: 6 | C10: 6 | D10: 6 | E10: Assumed academic-term use.
A11: Firm customers (active) | B11: 0 | C11: 5 | D11: 20 | E11: Employers with junior-staff programs.
A12: Seats per firm customer | B12: 100 | C12: 100 | D12: 100 | E12: Junior staff covered.
A13: Firm price ($ per seat per month) | B13: 15 | C13: 15 | D13: 15 | E13: Assumed.
A14: Firm months billed per year | B14: 12 | C14: 12 | D14: 12 | E14: Annual license.
A15: Grant income ($) | B15: 0 | C15: 0 | D15: 0 | E15: Set to 0. See the Grants sheet; none of the verified calls is open and a fit today.
A17: Costs
A18: AI helper cost ($ per seat-month) | B18: 1 | C18: 1 | D18: 1 | E18: Assumed model API cost per active seat-month if we host the helper.
A19: Share of seats on our hosted helper | B19: 0.5 | C19: 0.5 | D19: 0.5 | E19: 0% if customers bring their own AI account.
A20: Hosting and infrastructure ($/yr) | B20: 3000 | C20: 6000 | D20: 15000 | E20: Assumed.
A21: Item-bank development ($/yr) | B21: 5000 | C21: 10000 | D21: 20000 | E21: Assumed. Calibrated exercises for each skill domain.
A22: Legal, patent and ethics ($/yr) | B22: 8000 | C22: 5000 | D22: 5000 | E22: Assumed. Founder pay is NOT included anywhere in this model.
A23: Sales and support (% of revenue) | B23: 0.15 | C23: 0.15 | D23: 0.15 | E23: Assumed.
A25: Risk
A26: Probability the human pilot shows a benefit | B26: 0.4 | E26: Placeholder, not an estimate. Applied to school and firm subscription revenue only.

Sheet Revenue Model
A1: Revenue, costs and result ($)
A2: All cells are formulas driven by the Assumptions sheet. Founder pay is excluded.
A4: Line | B4: Year 1 | C4: Year 2 | D4: Year 3 | E4: 3-year total
A5: Revenue
A6: Pilot fees | B6: =Assumptions!B5*Assumptions!B6 -> 30000 | C6: =Assumptions!C5*Assumptions!C6 -> 0 | D6: =Assumptions!D5*Assumptions!D6 -> 0 | E6: =SUM(B6:D6) -> 30000
A7: School subscriptions | B7: =Assumptions!B7*Assumptions!B8*Assumptions!B9*Assumptions!B10 -> 0 | C7: =Assumptions!C7*Assumptions!C8*Assumptions!C9*Assumptions!C10 -> 60000 | D7: =Assumptions!D7*Assumptions!D8*Assumptions!D9*Assumptions!D10 -> 240000 | E7: =SUM(B7:D7) -> 300000
A8: Firm subscriptions | B8: =Assumptions!B11*Assumptions!B12*Assumptions!B13*Assumptions!B14 -> 0 | C8: =Assumptions!C11*Assumptions!C12*Assumptions!C13*Assumptions!C14 -> 90000 | D8: =Assumptions!D11*Assumptions!D12*Assumptions!D13*Assumptions!D14 -> 360000 | E8: =SUM(B8:D8) -> 450000
A9: Total revenue | B9: =SUM(B6:B8) -> 30000 | C9: =SUM(C6:C8) -> 150000 | D9: =SUM(D6:D8) -> 600000 | E9: =SUM(B9:D9) -> 780000
A10: Grant income | B10: =Assumptions!B15 -> 0 | C10: =Assumptions!C15 -> 0 | D10: =Assumptions!D15 -> 0 | E10: =SUM(B10:D10) -> 0
A12: Costs
A13: Paid seat-months | B13: =Assumptions!B7*Assumptions!B8*Assumptions!B10+Assumptions!B11*Assumptions!B12*Assumptions!B14 -> 0 | C13: =Assumptions!C7*Assumptions!C8*Assumptions!C10+Assumptions!C11*Assumptions!C12*Assumptions!C14 -> 18000 | D13: =Assumptions!D7*Assumptions!D8*Assumptions!D10+Assumptions!D11*Assumptions!D12*Assumptions!D14 -> 72000 | E13: =SUM(B13:D13) -> 90000
A14: AI helper cost | B14: =B13*Assumptions!B18*Assumptions!B19 -> 0 | C14: =C13*Assumptions!C18*Assumptions!C19 -> 9000 | D14: =D13*Assumptions!D18*Assumptions!D19 -> 36000 | E14: =SUM(B14:D14) -> 45000
A15: Hosting and infrastructure | B15: =Assumptions!B20 -> 3000 | C15: =Assumptions!C20 -> 6000 | D15: =Assumptions!D20 -> 15000 | E15: =SUM(B15:D15) -> 24000
A16: Item-bank development | B16: =Assumptions!B21 -> 5000 | C16: =Assumptions!C21 -> 10000 | D16: =Assumptions!D21 -> 20000 | E16: =SUM(B16:D16) -> 35000
A17: Legal, patent and ethics | B17: =Assumptions!B22 -> 8000 | C17: =Assumptions!C22 -> 5000 | D17: =Assumptions!D22 -> 5000 | E17: =SUM(B17:D17) -> 18000
A18: Sales and support | B18: =B9*Assumptions!B23 -> 4500 | C18: =C9*Assumptions!C23 -> 22500 | D18: =D9*Assumptions!D23 -> 90000 | E18: =SUM(B18:D18) -> 117000
A19: Total costs | B19: =SUM(B14:B18) -> 20500 | C19: =SUM(C14:C18) -> 52500 | D19: =SUM(D14:D18) -> 166000 | E19: =SUM(B19:D19) -> 239000
A21: Result
A22: Result if the pilot succeeds (revenue + grants - costs) | B22: =B9+B10-B19 -> 9500 | C22: =C9+C10-C19 -> 97500 | D22: =D9+D10-D19 -> 434000 | E22: =SUM(B22:D22) -> 541000
A23: Risk-adjusted revenue | B23: =B6+(B7+B8)*Assumptions!$B$26 -> 30000 | C23: =C6+(C7+C8)*Assumptions!$B$26 -> 60000 | D23: =D6+(D7+D8)*Assumptions!$B$26 -> 240000 | E23: =SUM(B23:D23) -> 330000
A24: Risk-adjusted result | B24: =B23+B10-B19-B18+B23*Assumptions!B23 -> 9500 | C24: =C23+C10-C19-C18+C23*Assumptions!C23 -> -6000 | D24: =D23+D10-D19-D18+D23*Assumptions!D23 -> 20000 | E24: =SUM(B24:D24) -> 23500
A26: Risk-adjusted result recomputes sales and support on the risk-adjusted revenue. Costs other than sales and support are kept in full, since they are spent whether or not the pilot succeeds.

Sheet Grants
A1: Funding calls checked on 11 Oct 2026
A2: Read from each call's own page or a news summary of it. Confirm on the funder's site before relying on any line. None was both open and a clear fit for an individual in Kenya today.
A4: Program | B4: Funder | C4: Status (11 Oct 2026) | D4: Deadline | E4: Size | F4: Who can apply | G4: Fit for this project | H4: Source
A5: Humanity AI Open Call | B5: Humanity AI, run with Lever for Change | C5: Open | D5: 21 Oct 2026 | E5: $75k-$1M, up to 3 years | F5: US-based organizations, or US-based individuals working with a 501(c)(3) sponsor. Research-only projects are out of scope. | G5: Stretch. Needs a US partner or fiscal sponsor and a deployment framing for education or labor. Ten days left. | H5: https://opportunitiesforyouth.org/2026/09/14/humanity-ai-open-call-2026-grants-of-up-to-1-million-for-community-led-ai-initiatives/
A6: Educational Technology Innovation Grants 2026/27 | B6: KENET (Kenya Education Network) | C6: Closed | D6: 10 Jul 2026 | E6: Not stated | F6: Lecturers with a PhD and 3+ years teaching the course at a Kenyan member university, with department and dean approval. | G6: Possible through a partner lecturer in the next cycle (AI in a foundational course, measured impact, shareable materials). | H6: https://www.kenet.or.ke/content/call-proposals-educational-technology-innovation-grants-20262027
A7: AI and Digital Technologies stream | B7: Science Granting Councils Initiative (SGCI) | C7: Closed | D7: 25 Sep 2026 | E7: CA$50k-$300k per member, up to 36 months | F7: Consortia of 3+ institutions from 3 different eligible countries (Kenya is named). | G7: Needs a university-led consortium. Watch for a later round. | H7: https://www.ictworks.org/digital-technology-research-in-africa/
A8: Innovating Education in Africa 2026 | B8: African Union (education, science and technology department) | C8: Closed | D8: 30 Apr 2026 | E8: Up to $50k, three winners | F8: African Union citizens leading a registered organization with verifiable results. Past winners excluded. | G8: Fit after the pilot gives results and a registered entity exists. Check whether it runs again. | H8: https://opportunitiesforyouth.org/2026/04/02/apply-now-african-union-call-for-submissions-up-to-50000-grants-for-edtech-tvet-ai-and-skills-development/
A9: Kenya AI Accelerator Programme 2026 | B9: MICDE, Technopolis Development Authority and UNDP Kenya | C9: Closed | D9: 6 Sep 2026 | E9: Non-cash: AI compute and technical support | F9: Kenya-based institutions, startups and innovators, in public-service or green-tech pathways. | G9: Weak. Education is not one of the pathways. Check if it reruns. | H9: https://www.globalsouthopportunities.com/2026/08/26/kenya-32/
A10: External Researcher Access Program | B10: Anthropic | C10: Rolling, reviewed monthly (confirm the form is live) | D10: First Monday of each month | E10: About $1,000 in API credits | F10: Mainly alignment researchers on AI safety topics. Not available where Claude is not offered. | G10: Weak. The focus is alignment. Credits could cover helper API costs in the pilot if it qualifies. | H10: https://support.claude.com/en/articles/9125743-what-is-the-external-researcher-access-program
